tradejournal/__init__.py
tradejournal/cli.py
tradejournal/store.py
tradejournal-0.1.0.dist-info/licenses/LICENSE
tradejournal-0.1.0.dist-info/METADATA
tradejournal-0.1.0.dist-info/WHEEL
tradejournal-0.1.0.dist-info/entry_points.txt
tradejournal-0.1.0.dist-info/top_level.txt
tradejournal-0.1.0.dist-info/RECORD
