Metadata-Version: 2.4
Name: tradejournal
Version: 0.1.0
Summary: Simple trade journal CLI
Author-email: Your Name <you@example.com>
Requires-Python: >=3.6
License-File: LICENSE
Requires-Dist: PyYAML>=5.0
Requires-Dist: rich>=10.0
Dynamic: license-file
